{
  "id": "step-10",
  "type": "question",
  "templateVersion": "3.0",
  "blocks": [
    {
      "id": "progress-10",
      "type": "question-progress",
      "order": 0,
      "properties": {
        "stepNumber": 10,
        "totalSteps": 21
      }
    },
    {
      "id": "number-10",
      "type": "question-number",
      "order": 1,
      "properties": {
        "questionNumber": "9 de 10"
      }
    },
    {
      "id": "text-10",
      "type": "question-text",
      "order": 2,
      "properties": {
        "questionText": "QUE TIPO DE ACESSÓRIOS VOCÊ GOSTA?"
      }
    },
    {
      "id": "instructions-10",
      "type": "question-instructions",
      "order": 3,
      "properties": {
        "requiredSelections": 3
      }
    },
    {
      "id": "options-10",
      "type": "options-grid",
      "order": 4,
      "properties": {
        "questionId": "step-10",
        "requiredSelections": 3,
        "multipleSelection": true,
        "showImages": true,
        "columns": 2,
        "options": [
          { "id": "natural", "text": "Pequenos e discretos, às vezes nem uso", "imageUrl": "https://res.cloudinary.com/dqljyf76t/image/upload/v1744735479/56_htzoxy.png" },
          { "id": "classico", "text": "Brincos pequenos e discretos. Corrente fininha", "imageUrl": "https://res.cloudinary.com/dqljyf76t/image/upload/v1744735479/57_whzmff.png" },
          { "id": "contemporaneo", "text": "Acessórios que elevem meu look com um toque moderno", "imageUrl": "https://res.cloudinary.com/dqljyf76t/image/upload/v1744735482/61_joafud.png" },
          { "id": "elegante", "text": "Acessórios sofisticados, joias ou semijoias", "imageUrl": "https://res.cloudinary.com/dqljyf76t/image/upload/v1744735482/60_vzsnps.png" },
          { "id": "romantico", "text": "Peças delicadas e com um toque feminino", "imageUrl": "https://res.cloudinary.com/dqljyf76t/image/upload/v1744735482/59_dwaqrx.png" },
          { "id": "sexy", "text": "Brincos longos, colares que valorizem minha beleza", "imageUrl": "https://res.cloudinary.com/dqljyf76t/image/upload/v1744735487/63_lwgokn.png" },
          { "id": "dramatico", "text": "Acessórios pesados, que causem um impacto", "imageUrl": "https://res.cloudinary.com/dqljyf76t/image/upload/v1744735485/62_mno8wg.png" },
          { "id": "criativo", "text": "Acessórios diferentes, grandes e marcantes", "imageUrl": "https://res.cloudinary.com/dqljyf76t/image/upload/v1744735480/58_njdjoh.png" }
        ]
      }
    },
    {
      "id": "navigation-10",
      "type": "question-navigation",
      "order": 5,
      "properties": {}
    }
  ],
  "meta": {
    "order": 10
  }
}
